estimator_wrapper/__init__.py
estimator_wrapper-2.1.dist-info/METADATA
estimator_wrapper-2.1.dist-info/WHEEL
estimator_wrapper-2.1.dist-info/top_level.txt
estimator_wrapper-2.1.dist-info/RECORD
