Metadata-Version: 2.1
Name: estimator-wrapper
Version: 2.1
Summary: Estimator Wrapper
Author: Wu Wenmin
Author-email: wuwenmin1991@gmail.com
License: MIT
Platform: UNKNOWN
